pydest/__init__.py
pydest/api.py
pydest/dbase.py
pydest/manifest.py
pydest/pydest.py
pydest/test/__init__.py
pydest/test/test_integration.py
pydest/test/test_pydest.py
pydest-0.6.1.dist-info/LICENSE.md
pydest-0.6.1.dist-info/METADATA
pydest-0.6.1.dist-info/WHEEL
pydest-0.6.1.dist-info/top_level.txt
pydest-0.6.1.dist-info/RECORD
