Metadata-Version: 2.1
Name: pydest
Version: 0.6.1
Summary: Async wrapper for Destiny 2 API
Home-page: https://github.com/jgayfer/pydest
Author: James Gayfer
Author-email: gayfer.james@gmail.com
License: UNKNOWN
Platform: UNKNOWN
Classifier: Programming Language :: Python :: 3
Classifier: License :: OSI Approved :: MIT License
Classifier: Operating System :: OS Independent
License-File: LICENSE.md
